Workbook

Sheet Dashboard
A1: CORPORATE OPERATIONS CENTER | PROJECT CONTROLS DASHBOARD
A3: Status Date | B3: 46276 | C3: Project Start | D3: 46034 | E3: Contract Finish | F3: 46465 | G3: Approved Budget | H3: 20600000 | I3: Project Manager | J3: Portfolio Simulation
A5: Revised Budget | C5: Forecast at Completion | E5: Forecast Variance | G5: Actual Cost to Date | I5: Open RFIs | K5: Open Risks
A6: =SUM(Budget_Cost!E2:E16) -> 21057000 | C6: =SUM(Budget_Cost!I2:I16) -> 20550000 | E6: =A6-C6 -> 507000 | G6: =SUM(Budget_Cost!G2:G16) -> 10215000 | I6: =COUNTIF(RFI_Log!I2:I16,"Open") -> 3 | K6: =COUNTIF(Risk_Register!L2:L9,"Open") -> 8
A8: Planned Progress | C8: Actual Progress | E8: Schedule Variance | G8: Approved Changes | I8: Open Actions | K8: Recordable Incidents
A9: =AVERAGE(Master_Schedule!K2:K35) -> 0.51676471 | C9: =AVERAGE(Master_Schedule!L2:L35) -> 0.49852941 | E9: =C9-A9 -> -0.018235294 | G9: =SUM(Change_Log!G2:G13) -> 564500 | I9: =COUNTIFS(Meeting_Actions!H2:H9,"<>Complete") -> 8 | K9: =COUNTIF(Safety_Log!J2:J9,"Yes") -> 0
A12: MANAGEMENT HEALTH SUMMARY | H12: NEXT 30 DAYS - KEY MILESTONES
A13: Area | B13: Health | C13: Key Driver | E13: Immediate Management Action | H13: Milestone | I13: Baseline | J13: Forecast | K13: Owner | L13: Risk
A14: Schedule | B14: AMBER | C14: Weather-tight milestone and MEP Area A are behind plan | E14: Recover south elevation framing; protect dry-in milestone | H14: AHU / RTU crane set | I14: 09/18/2026 | J14: 09/17/2026 | K14: Mechanical | L14: Low
A15: Cost | B15: AMBER | C15: Forecast remains within budget but contingency is tightening | E15: Escalate elective owner changes; protect remaining contingency | H15: Weather-tight milestone | I15: 09/25/2026 | J15: 09/29/2026 | K15: GC / Envelope | L15: High
A16: Procurement | B16: GREEN | C16: Major long-leads released; electrical gear remains on critical watch | E16: Hold weekly factory call and maintain expedite decision gate | H16: Electrical gear ship | I16: 09/28/2026 | J16: 09/28/2026 | K16: Electrical | L16: Medium
A17: Safety | B17: GREEN | C17: Zero recordables; one open scaffold observation | E17: Close observation before next shift; continue leading-edge audits | H17: Interior framing start | I17: 09/28/2026 | J17: 09/30/2026 | K17: GC / Framing | L17: Medium
A18: Quality | B18: AMBER | C18: One open MEP rough-in deficiency at Grid C7 | E18: Close clash and reinspect before downstream enclosure | H18: Area A MEP rough-in complete | I18: 10/02/2026 | J18: 10/09/2026 | K18: MEP | L18: High

Sheet Master_Schedule
A1: WBS | B1: Phase | C1: Activity | D1: Owner | E1: Planned Start | F1: Planned Finish | G1: Actual Start | H1: Actual Finish | I1: Duration (d) | J1: Predecessor | K1: Planned % | L1: Actual % | M1: Status | N1: Variance (pp) | O1: Critical? | P1: Notes
A2: 1.1 | B2: Preconstruction | C2: Owner program validation | D2: PM | E2: 46034 | F2: 46045 | G2: 46034 | H2: 46044 | I2: 12 | K2: 1 | L2: 1 | M2: Complete | N2: =L2-K2 -> 0 | O2: No | P2: Program signed off one day early
A3: 1.2 | B3: Preconstruction | C3: Design development / 60% CDs | D3: Architect | E3: 46041 | F3: 46073 | G3: 46041 | H3: 46077 | I3: 33 | J3: 1.1 | K3: 1 | L3: 1 | M3: Complete | N3: =L3-K3 -> 0 | O3: Yes | P3: Four-day delay absorbed by bid prep
A4: 1.3 | B4: Preconstruction | C4: 100% construction documents | D4: Architect | E4: 46076 | F4: 46108 | G4: 46078 | H4: 46114 | I4: 33 | J4: 1.2 | K4: 1 | L4: 1 | M4: Complete | N4: =L4-K4 -> 0 | O4: Yes | P4: MEP coordination drove six-day slip
A5: 1.4 | B5: Preconstruction | C5: Permit review and issuance | D5: PM/Architect | E5: 46083 | F5: 46122 | G5: 46083 | H5: 46126 | I5: 40 | J5: 1.3 | K5: 1 | L5: 1 | M5: Complete | N5: =L5-K5 -> 0 | O5: Yes | P5: Permit issued 4/14
A6: 1.5 | B6: Procurement | C6: Bid packages and subcontract awards | D6: PM | E6: 46069 | F6: 46115 | G6: 46069 | H6: 46119 | I6: 47 | J6: 1.2 | K6: 1 | L6: 1 | M6: Complete | N6: =L6-K6 -> 0 | O6: No | P6: Major trades bought out
A7: 2.1 | B7: Mobilization | C7: Site mobilization / temporary controls | D7: Superintendent | E7: 46125 | F7: 46136 | G7: 46127 | H7: 46136 | I7: 12 | J7: 1.4,1.5 | K7: 1 | L7: 1 | M7: Complete | N7: =L7-K7 -> 0 | O7: Yes | P7: Mobilization started after permit
A8: 2.2 | B8: Sitework | C8: Clearing and erosion controls | D8: Sitework Sub | E8: 46132 | F8: 46150 | G8: 46134 | H8: 46153 | I8: 19 | J8: 2.1 | K8: 1 | L8: 1 | M8: Complete | N8: =L8-K8 -> 0 | O8: Yes | P8: Rain impacted 3 days
A9: 2.3 | B9: Sitework | C9: Mass grading and underground utilities | D9: Sitework Sub | E9: 46146 | F9: 46185 | G9: 46148 | H9: 46191 | I9: 40 | J9: 2.2 | K9: 1 | L9: 1 | M9: Complete | N9: =L9-K9 -> 0 | O9: Yes | P9: Utility conflict required RFI-006
A10: 3.1 | B10: Foundations | C10: Footings and grade beams | D10: Concrete Sub | E10: 46167 | F10: 46192 | G10: 46170 | H10: 46197 | I10: 26 | J10: 2.3 | K10: 1 | L10: 1 | M10: Complete | N10: =L10-K10 -> 0 | O10: Yes | P10: Recovered two days with added crew
A11: 3.2 | B11: Foundations | C11: Slab-on-grade | D11: Concrete Sub | E11: 46188 | F11: 46213 | G11: 46193 | H11: 46218 | I11: 26 | J11: 3.1 | K11: 1 | L11: 1 | M11: Complete | N11: =L11-K11 -> 0 | O11: Yes | P11: Passed FF/FL testing
A12: 4.1 | B12: Structure | C12: Structural steel fabrication | D12: Steel Sub | E12: 46132 | F12: 46206 | G12: 46134 | H12: 46213 | I12: 75 | J12: 1.5 | K12: 1 | L12: 1 | M12: Complete | N12: =L12-K12 -> 0 | O12: Yes | P12: Long-lead shop drawing cycle
A13: 4.2 | B13: Structure | C13: Structural steel erection | D13: Steel Sub | E13: 46216 | F13: 46255 | G13: 46219 | H13: 46262 | I13: 40 | J13: 3.2,4.1 | K13: 1 | L13: 1 | M13: Complete | N13: =L13-K13 -> 0 | O13: Yes | P13: Completed one week late
A14: 4.3 | B14: Structure | C14: Metal deck and concrete elevated slab | D14: Steel/Concrete | E14: 46237 | F14: 46269 | G14: 46244 | I14: 33 | J14: 4.2 | K14: 1 | L14: 0.88 | M14: In Progress | N14: =L14-K14 -> -0.12 | O14: Yes | P14: Deck pour sequence recovering schedule
A15: 5.1 | B15: Envelope | C15: Exterior framing and sheathing | D15: Framing Sub | E15: 46251 | F15: 46290 | G15: 46258 | I15: 40 | J15: 4.2 | K15: 0.75 | L15: 0.62 | M15: In Progress | N15: =L15-K15 -> -0.13 | O15: Yes | P15: South elevation 5 days behind
A16: 5.2 | B16: Envelope | C16: Roofing system | D16: Roofing Sub | E16: 46265 | F16: 46290 | G16: 46268 | I16: 26 | J16: 4.3 | K16: 0.45 | L16: 0.38 | M16: In Progress | N16: =L16-K16 -> -0.07 | O16: Yes | P16: Weather-tight target 9/29
A17: 5.3 | B17: Envelope | C17: Curtain wall / storefront | D17: Glazing Sub | E17: 46272 | F17: 46311 | G17: 46274 | I17: 40 | J17: 5.1 | K17: 0.15 | L17: 0.08 | M17: In Progress | N17: =L17-K17 -> -0.07 | O17: No | P17: Frames arriving in 2 lots
A18: 6.1 | B18: MEP | C18: Underground electrical and plumbing | D18: MEP Subs | E18: 46160 | F18: 46220 | G18: 46162 | H18: 46224 | I18: 61 | J18: 2.3 | K18: 1 | L18: 1 | M18: Complete | N18: =L18-K18 -> 0 | O18: No | P18: Completed
A19: 6.2 | B19: MEP | C19: MEP overhead rough-in - Area A | D19: MEP Subs | E19: 46258 | F19: 46297 | G19: 46265 | I19: 40 | J19: 4.3 | K19: 0.5 | L19: 0.35 | M19: In Progress | N19: =L19-K19 -> -0.15 | O19: Yes | P19: Coordination issue at grid C7
A20: 6.3 | B20: MEP | C20: MEP overhead rough-in - Area B | D20: MEP Subs | E20: 46279 | F20: 46318 | I20: 40 | J20: 6.2 | K20: 0 | L20: 0 | M20: Not Started | N20: =L20-K20 -> 0 | O20: Yes | P20: Release after Area A inspection
A21: 6.4 | B21: MEP | C21: Main electrical gear delivery | D21: Electrical Sub | E21: 46146 | F21: 46304 | G21: 46146 | I21: 159 | J21: 1.5 | K21: 0.8 | L21: 0.76 | M21: In Progress | N21: =L21-K21 -> -0.04 | O21: Yes | P21: Factory ship date confirmed 9/28
A22: 6.5 | B22: MEP | C22: AHU / RTU delivery and set | D22: Mechanical Sub | E22: 46153 | F22: 46283 | G22: 46153 | I22: 131 | J22: 1.5 | K22: 0.92 | L22: 0.88 | M22: In Progress | N22: =L22-K22 -> -0.04 | O22: Yes | P22: Crane set planned 9/17
A23: 7.1 | B23: Interiors | C23: Interior metal framing | D23: Framing Sub | E23: 46293 | F23: 46332 | I23: 40 | J23: 5.2,6.2 | K23: 0 | L23: 0 | M23: Not Started | N23: =L23-K23 -> 0 | O23: Yes | P23: Start after dry-in
A24: 7.2 | B24: Interiors | C24: Drywall / tape / finish | D24: Drywall Sub | E24: 46314 | F24: 46360 | I24: 47 | J24: 7.1 | K24: 0 | L24: 0 | M24: Not Started | N24: =L24-K24 -> 0 | O24: Yes
A25: 7.3 | B25: Interiors | C25: Ceilings and flooring | D25: Finishes Subs | E25: 46349 | F25: 46402 | I25: 54 | J25: 7.2 | K25: 0 | L25: 0 | M25: Not Started | N25: =L25-K25 -> 0 | O25: No
A26: 7.4 | B26: Interiors | C26: Millwork / doors / hardware | D26: Carpentry Sub | E26: 46356 | F26: 46409 | I26: 54 | J26: 7.2 | K26: 0 | L26: 0 | M26: Not Started | N26: =L26-K26 -> 0 | O26: No
A27: 7.5 | B27: Interiors | C27: Painting and final finishes | D27: Painting Sub | E27: 46363 | F27: 46416 | I27: 54 | J27: 7.2 | K27: 0 | L27: 0 | M27: Not Started | N27: =L27-K27 -> 0 | O27: No
A28: 8.1 | B28: Sitework | C28: Paving, curb, sidewalks | D28: Sitework Sub | E28: 46300 | F28: 46339 | I28: 40 | J28: 5.1 | K28: 0 | L28: 0 | M28: Not Started | N28: =L28-K28 -> 0 | O28: No
A29: 8.2 | B29: Sitework | C29: Landscaping and site furnishings | D29: Landscape Sub | E29: 46391 | F29: 46423 | I29: 33 | J29: 8.1 | K29: 0 | L29: 0 | M29: Not Started | N29: =L29-K29 -> 0 | O29: No
A30: 9.1 | B30: Commissioning | C30: MEP startup and controls checkout | D30: CxA/MEP | E30: 46398 | F30: 46430 | I30: 33 | J30: 6.4,6.5,7.3 | K30: 0 | L30: 0 | M30: Not Started | N30: =L30-K30 -> 0 | O30: Yes
A31: 9.2 | B31: Commissioning | C31: TAB / functional performance testing | D31: CxA | E31: 46419 | F31: 46444 | I31: 26 | J31: 9.1 | K31: 0 | L31: 0 | M31: Not Started | N31: =L31-K31 -> 0 | O31: Yes
A32: 9.3 | B32: Closeout | C32: Punch list and deficiency correction | D32: PM/Superintendent | E32: 46433 | F32: 46451 | I32: 19 | J32: 7.5,9.2 | K32: 0 | L32: 0 | M32: Not Started | N32: =L32-K32 -> 0 | O32: Yes
A33: 9.4 | B33: Closeout | C33: Owner training / O&M turnover | D33: PM/CxA | E33: 46440 | F33: 46458 | I33: 19 | J33: 9.1 | K33: 0 | L33: 0 | M33: Not Started | N33: =L33-K33 -> 0 | O33: No
A34: 9.5 | B34: Closeout | C34: Certificate of Occupancy | D34: PM/Architect | E34: 46454 | F34: 46458 | I34: 5 | J34: 9.3 | K34: 0 | L34: 0 | M34: Not Started | N34: =L34-K34 -> 0 | O34: Yes
A35: 9.6 | B35: Closeout | C35: Final completion / handover | D35: PM | E35: 46461 | F35: 46465 | I35: 5 | J35: 9.4,9.5 | K35: 0 | L35: 0 | M35: Not Started | N35: =L35-K35 -> 0 | O35: Yes

Sheet Budget_Cost
A1: Cost Code | B1: Cost Category | C1: Original Budget | D1: Approved Changes | E1: Revised Budget | F1: Committed | G1: Actual Cost to Date | H1: ETC | I1: Forecast at Completion | J1: Variance to Budget | K1: % Committed | L1: % Spent | M1: Status | N1: Notes
A2: 01-100 | B2: General Conditions | C2: 1350000 | D2: 125000 | E2: =C2+D2 -> 1475000 | F2: 1445000 | G2: 970000 | H2: 510000 | I2: =G2+H2 -> 1480000 | J2: =E2-I2 -> -5000 | K2: =IF(E2=0,0,F2/E2) -> 0.97966102 | L2: =IF(E2=0,0,G2/E2) -> 0.65762712 | M2: Watch | N2: Extended supervision due to early schedule slippage
A3: 02-200 | B3: Sitework & Utilities | C3: 1820000 | D3: 85000 | E3: =C3+D3 -> 1905000 | F3: 1880000 | G3: 1735000 | H3: 170000 | I3: =G3+H3 -> 1905000 | J3: =E3-I3 -> 0 | K3: =IF(E3=0,0,F3/E3) -> 0.98687664 | L3: =IF(E3=0,0,G3/E3) -> 0.91076115 | M3: On Budget | N3: Utility conflict resolved
A4: 03-300 | B4: Concrete | C4: 2050000 | D4: 45000 | E4: =C4+D4 -> 2095000 | F4: 2075000 | G4: 1960000 | H4: 155000 | I4: =G4+H4 -> 2115000 | J4: =E4-I4 -> -20000 | K4: =IF(E4=0,0,F4/E4) -> 0.99045346 | L4: =IF(E4=0,0,G4/E4) -> 0.93556086 | M4: On Budget | N4: Minor premium for recovery crew
A5: 05-500 | B5: Structural Steel | C5: 2790000 | D5: 210000 | E5: =C5+D5 -> 3000000 | F5: 2945000 | G5: 2385000 | H5: 590000 | I5: =G5+H5 -> 2975000 | J5: =E5-I5 -> 25000 | K5: =IF(E5=0,0,F5/E5) -> 0.98166667 | L5: =IF(E5=0,0,G5/E5) -> 0.795 | M5: Watch | N5: Escalation and connection redesign
A6: 07-700 | B6: Roofing & Waterproofing | C6: 840000 | D6: 0 | E6: =C6+D6 -> 840000 | F6: 810000 | G6: 180000 | H6: 640000 | I6: =G6+H6 -> 820000 | J6: =E6-I6 -> 20000 | K6: =IF(E6=0,0,F6/E6) -> 0.96428571 | L6: =IF(E6=0,0,G6/E6) -> 0.21428571 | M6: On Budget | N6: Buyout savings retained
A7: 08-800 | B7: Glazing / Doors / Hardware | C7: 1260000 | D7: 95000 | E7: =C7+D7 -> 1355000 | F7: 1325000 | G7: 230000 | H7: 1090000 | I7: =G7+H7 -> 1320000 | J7: =E7-I7 -> 35000 | K7: =IF(E7=0,0,F7/E7) -> 0.97785978 | L7: =IF(E7=0,0,G7/E7) -> 0.1697417 | M7: Watch | N7: Storefront upgrade approved
A8: 09-900 | B8: Interiors / Finishes | C8: 2190000 | D8: -65000 | E8: =C8+D8 -> 2125000 | F8: 2080000 | G8: 250000 | H8: 1810000 | I8: =G8+H8 -> 2060000 | J8: =E8-I8 -> 65000 | K8: =IF(E8=0,0,F8/E8) -> 0.97882353 | L8: =IF(E8=0,0,G8/E8) -> 0.11764706 | M8: On Budget | N8: VE package reduced ceiling scope
A9: 21-2300 | B9: Fire Protection | C9: 510000 | D9: 0 | E9: =C9+D9 -> 510000 | F9: 495000 | G9: 145000 | H9: 345000 | I9: =G9+H9 -> 490000 | J9: =E9-I9 -> 20000 | K9: =IF(E9=0,0,F9/E9) -> 0.97058824 | L9: =IF(E9=0,0,G9/E9) -> 0.28431373 | M9: On Budget
A10: 22-2200 | B10: Plumbing | C10: 780000 | D10: 42000 | E10: =C10+D10 -> 822000 | F10: 805000 | G10: 315000 | H10: 500000 | I10: =G10+H10 -> 815000 | J10: =E10-I10 -> 7000 | K10: =IF(E10=0,0,F10/E10) -> 0.97931873 | L10: =IF(E10=0,0,G10/E10) -> 0.38321168 | M10: On Budget | N10: Added floor sinks
A11: 23-2300 | B11: HVAC / Controls | C11: 1810000 | D11: 120000 | E11: =C11+D11 -> 1930000 | F11: 1885000 | G11: 525000 | H11: 1410000 | I11: =G11+H11 -> 1935000 | J11: =E11-I11 -> -5000 | K11: =IF(E11=0,0,F11/E11) -> 0.97668394 | L11: =IF(E11=0,0,G11/E11) -> 0.27202073 | M11: Watch | N11: Controls integration allowance
A12: 26-2600 | B12: Electrical / Low Voltage | C12: 2030000 | D12: 165000 | E12: =C12+D12 -> 2195000 | F12: 2135000 | G12: 635000 | H12: 1545000 | I12: =G12+H12 -> 2180000 | J12: =E12-I12 -> 15000 | K12: =IF(E12=0,0,F12/E12) -> 0.97266515 | L12: =IF(E12=0,0,G12/E12) -> 0.28929385 | M12: Watch | N12: Main gear expedite allowance
A13: 31-3200 | B13: Paving / Landscaping | C13: 760000 | D13: 0 | E13: =C13+D13 -> 760000 | F13: 720000 | G13: 85000 | H13: 615000 | I13: =G13+H13 -> 700000 | J13: =E13-I13 -> 60000 | K13: =IF(E13=0,0,F13/E13) -> 0.94736842 | L13: =IF(E13=0,0,G13/E13) -> 0.11184211 | M13: On Budget
A14: 00-900 | B14: Design / Permits / Testing | C14: 790000 | D14: 55000 | E14: =C14+D14 -> 845000 | F14: 835000 | G14: 690000 | H14: 145000 | I14: =G14+H14 -> 835000 | J14: =E14-I14 -> 10000 | K14: =IF(E14=0,0,F14/E14) -> 0.98816568 | L14: =IF(E14=0,0,G14/E14) -> 0.81656805 | M14: On Budget | N14: Additional special inspections
A15: 00-950 | B15: Owner FF&E / IT Allowance | C15: 900000 | D15: 0 | E15: =C15+D15 -> 900000 | F15: 610000 | G15: 110000 | H15: 510000 | I15: =G15+H15 -> 620000 | J15: =E15-I15 -> 280000 | K15: =IF(E15=0,0,F15/E15) -> 0.67777778 | L15: =IF(E15=0,0,G15/E15) -> 0.12222222 | M15: On Budget | N15: Owner-direct packages
A16: 00-990 | B16: Construction Contingency | C16: 720000 | D16: -420000 | E16: =C16+D16 -> 300000 | F16: 0 | G16: 0 | H16: 300000 | I16: =G16+H16 -> 300000 | J16: =E16-I16 -> 0 | K16: =IF(E16=0,0,F16/E16) -> 0 | L16: =IF(E16=0,0,G16/E16) -> 0 | M16: Watch | N16: $420K allocated through approved changes

Sheet Procurement
A1: Package | B1: Trade/Vendor | C1: Scope | D1: Budget | E1: Bid Due | F1: Award Date | G1: Submittal Due | H1: Required On Site | I1: Current Forecast | J1: Lead Time (wks) | K1: Status | L1: Owner | M1: Risk/Action
A2: BP-01 | B2: Carolina Earthworks | C2: Sitework / utilities | D2: 1820000 | E2: 46080 | F2: 46094 | G2: 46108 | H2: 46132 | I2: 46134 | J2: 5 | K2: Complete | L2: PM | M2: Closed
A3: BP-02 | B3: Piedmont Concrete | C3: Foundations / slabs | D3: 2050000 | E3: 46087 | F3: 46101 | G3: 46115 | H3: 46167 | I3: 46170 | J3: 8 | K3: Complete | L3: PM | M3: Closed
A4: BP-03 | B4: SteelWorks Southeast | C4: Structural steel | D4: 2790000 | E4: 46073 | F4: 46087 | G4: 46101 | H4: 46216 | I4: 46219 | J4: 18 | K4: Complete | L4: PM | M4: Late detailing; recovery complete
A5: BP-04 | B5: Atlantic Roofing | C5: Roofing | D5: 840000 | E5: 46094 | F5: 46108 | G5: 46122 | H5: 46265 | I5: 46268 | J5: 12 | K5: In Progress | L5: PM | M5: Monitor membrane delivery
A6: BP-05 | B6: ClearView Glazing | C6: Curtain wall / storefront | D6: 1260000 | E6: 46094 | F6: 46108 | G6: 46122 | H6: 46272 | I6: 46274 | J6: 20 | K6: In Progress | L6: PM | M6: Frames split into two shipments
A7: BP-06 | B7: Precision Mechanical | C7: HVAC / controls | D7: 1810000 | E7: 46080 | F7: 46094 | G7: 46108 | H7: 46279 | I7: 46282 | J7: 24 | K7: In Progress | L7: PM | M7: RTU crane set locked for 9/17
A8: BP-07 | B8: Triad Electrical | C8: Electrical / low voltage | D8: 2030000 | E8: 46080 | F8: 46094 | G8: 46108 | H8: 46304 | I8: 46300 | J8: 28 | K8: In Progress | L8: PM | M8: Gear ship 9/28; 4-day float
A9: BP-08 | B9: Interior Systems Inc. | C9: Framing / drywall / ceilings | D9: 2190000 | E9: 46115 | F9: 46129 | G9: 46143 | H9: 46293 | I9: 46293 | J9: 10 | K9: Awarded | L9: PM | M9: Release Area A material now
A10: BP-09 | B10: FinishWorks | C10: Flooring / paint | D10: 940000 | E10: 46143 | F10: 46157 | G10: 46174 | H10: 46349 | I10: 46349 | J10: 12 | K10: Awarded | L10: PM | M10: Mockups due 10/16
A11: BP-10 | B11: OfficeTech Integrators | C11: AV / access control / data | D11: 610000 | E11: 46185 | F11: 46199 | G11: 46213 | H11: 46391 | I11: 46391 | J11: 18 | K11: Awarded | L11: Owner IT | M11: Coordinate with ceilings

Sheet RFI_Log
A1: RFI # | B1: Date Submitted | C1: Discipline | D1: Subject | E1: Submitted By | F1: Ball In Court | G1: Due Date | H1: Answered Date | I1: Status | J1: Schedule Impact (days) | K1: Cost Impact | L1: Related CO | M1: Resolution / Decision
A2: RFI-001 | B2: 46139 | C2: Civil | D2: Storm line invert conflict at east drive | E2: Sitework Sub | F2: Civil Engineer | G2: 46143 | H2: 46142 | I2: Closed | J2: 0 | K2: 0 | M2: Revise invert and add cleanout
A3: RFI-002 | B3: 46160 | C3: Structural | D3: Footing F12 clashes with telecom ductbank | E3: Concrete Sub | F3: Structural Engineer | G3: 46164 | H3: 46163 | I3: Closed | J3: 0 | K3: 12500 | L3: CO-002 | M3: Shift footing 18 inches west
A4: RFI-003 | B4: 46175 | C4: Architectural | D4: Lobby stone backing detail | E4: Framing Sub | F4: Architect | G4: 46181 | H4: 46182 | I4: Closed | J4: 1 | K4: 4500 | M4: Supplemental stud framing approved
A5: RFI-004 | B5: 46192 | C5: Structural | D5: Beam camber tolerance at grid D | E5: Steel Sub | F5: Structural Engineer | G5: 46198 | H5: 46197 | I5: Closed | J5: 0 | K5: 0 | M5: Accept per tolerance; field survey required
A6: RFI-005 | B6: 46210 | C6: Mechanical | D6: Roof curb opening dimensions | E6: Mechanical Sub | F6: Architect/MEP | G6: 46216 | H6: 46213 | I6: Closed | J6: 0 | K6: 0 | M6: Use vendor-certified curb dimensions
A7: RFI-006 | B7: 46171 | C7: Civil | D7: Unknown utility crossing north service yard | E7: Sitework Sub | F7: Civil Engineer | G7: 46177 | H7: 46181 | I7: Closed | J7: 3 | K7: 68500 | L7: CO-004 | M7: Reroute sanitary around existing fiber bank
A8: RFI-007 | B8: 46230 | C8: Architectural | D8: Storefront head condition at canopy | E8: Glazing Sub | F8: Architect | G8: 46237 | H8: 46239 | I8: Closed | J8: 2 | K8: 18000 | L8: CO-006 | M8: Add steel tube support at head
A9: RFI-008 | B9: 46245 | C9: MEP | D9: Duct / sprinkler clash above training room | E9: Mechanical Sub | F9: MEP Engineer | G9: 46251 | H9: 46248 | I9: Closed | J9: 0 | K9: 0 | M9: Raise branch line 4 inches
A10: RFI-009 | B10: 46254 | C10: Electrical | D10: Generator feeder routing through shear wall | E10: Electrical Sub | F10: MEP/Structural | G10: 46260 | H10: 46265 | I10: Closed | J10: 2 | K10: 22500 | L10: CO-008 | M10: Core sleeve detail issued
A11: RFI-010 | B11: 46265 | C11: Architectural | D11: Exterior panel transition at loading dock | E11: Envelope Sub | F11: Architect | G11: 46269 | H11: 46273 | I11: Answered | J11: 1 | K11: 7500 | M11: Revised flashing detail A-521
A12: RFI-011 | B12: 46267 | C12: Mechanical | D12: AHU condensate routing at mezzanine | E12: Mechanical Sub | F12: MEP Engineer | G12: 46274 | H12: 46274 | I12: Answered | J12: 0 | K12: 3200 | M12: Route to nearby hub drain
A13: RFI-012 | B13: 46269 | C13: Structural | D13: Deck penetration reinforcing at RTU-3 | E13: Steel Sub | F13: Structural Engineer | G13: 46275 | H13: 46275 | I13: Answered | J13: 0 | K13: 6400 | M13: Add angle frame per SK-S14
A14: RFI-013 | B14: 46273 | C14: Electrical | D14: Lighting control zone revision in open office | E14: Electrical Sub | F14: Architect/Owner | G14: 46279 | I14: Open | J14: 0 | K14: 18000 | L14: PCO-012 | M14: Owner decision pending
A15: RFI-014 | B15: 46274 | C15: Architectural | D15: Door 214 hardware function | E15: Door Sub | F15: Architect | G15: 46280 | I15: Open | J15: 0 | K15: 0 | M15: Confirm electrified panic hardware
A16: RFI-015 | B16: 46275 | C16: MEP | D16: Domestic water meter backflow arrangement | E16: Plumbing Sub | F16: MEP Engineer | G16: 46281 | I16: Open | J16: 0 | K16: 0 | M16: Awaiting utility confirmation

Sheet Submittal_Log
A1: Submittal # | B1: Spec Section | C1: Package | D1: Description | E1: Trade | F1: Submitted | G1: Review Due | H1: Returned | I1: Status | J1: Rev | K1: Required On Site | L1: Days Float | M1: Notes
A2: SUB-001 | B2: 03 30 00 | C2: BP-02 | D2: Concrete mix designs | E2: Piedmont Concrete | F2: 46111 | G2: 46118 | H2: 46115 | I2: Approved | J2: 0 | K2: 46167 | L2: 52
A3: SUB-002 | B3: 05 12 00 | C3: BP-03 | D3: Structural steel shop drawings | E3: SteelWorks Southeast | F3: 46104 | G3: 46118 | H3: 46126 | I3: Revise & Resubmit | J3: 0 | K3: 46174 | L3: 48 | M3: Second cycle expedited
A4: SUB-003 | B4: 05 12 00 | C4: BP-03 | D4: Structural steel shop drawings - Rev 1 | E4: SteelWorks Southeast | F4: 46129 | G4: 46136 | H4: 46135 | I4: Approved | J4: 1 | K4: 46174 | L4: 39 | M4: Released to fabrication
A5: SUB-004 | B5: 07 54 23 | C5: BP-04 | D5: TPO roofing system | E5: Atlantic Roofing | F5: 46125 | G5: 46139 | H5: 46136 | I5: Approved | J5: 0 | K5: 46265 | L5: 129
A6: SUB-005 | B6: 08 41 13 | C6: BP-05 | D6: Aluminum storefront / curtain wall | E6: ClearView Glazing | F6: 46132 | G6: 46146 | H6: 46149 | I6: Revise & Resubmit | J6: 0 | K6: 46272 | L6: 123 | M6: Head condition revised
A7: SUB-006 | B7: 08 41 13 | C7: BP-05 | D7: Storefront / curtain wall - Rev 1 | E7: ClearView Glazing | F7: 46153 | G7: 46160 | H7: 46160 | I7: Approved | J7: 1 | K7: 46272 | L7: 112 | M7: Released
A8: SUB-007 | B8: 23 73 00 | C8: BP-06 | D8: Packaged rooftop units | E8: Precision Mechanical | F8: 46111 | G8: 46125 | H8: 46122 | I8: Approved | J8: 0 | K8: 46279 | L8: 157 | M8: Long lead released
A9: SUB-008 | B9: 26 24 13 | C9: BP-07 | D9: Main switchboard / distribution gear | E9: Triad Electrical | F9: 46104 | G9: 46118 | H9: 46120 | I9: Approved | J9: 0 | K9: 46304 | L9: 184 | M9: Critical long lead
A10: SUB-009 | B10: 09 29 00 | C10: BP-08 | D10: Gypsum board assemblies | E10: Interior Systems Inc. | F10: 46216 | G10: 46230 | H10: 46227 | I10: Approved | J10: 0 | K10: 46293 | L10: 66
A11: SUB-010 | B11: 09 51 00 | C11: BP-08 | D11: Acoustical ceiling systems | E11: Interior Systems Inc. | F11: 46237 | G11: 46251 | H11: 46252 | I11: Approved | J11: 0 | K11: 46349 | L11: 97
A12: SUB-011 | B12: 09 65 00 | C12: BP-09 | D12: Resilient flooring samples | E12: FinishWorks | F12: 46251 | G12: 46265 | H12: 46262 | I12: Approved | J12: 0 | K12: 46349 | L12: 87 | M12: Mockup required
A13: SUB-012 | B13: 09 91 00 | C13: BP-09 | D13: Paint color samples | E13: FinishWorks | F13: 46258 | G13: 46272 | H13: 46269 | I13: Approved | J13: 0 | K13: 46363 | L13: 94
A14: SUB-013 | B14: 28 13 00 | C14: BP-10 | D14: Access control head-end | E14: OfficeTech Integrators | F14: 46265 | G14: 46279 | I14: Submitted | J14: 0 | K14: 46391 | L14: 112 | M14: Review due
A15: SUB-014 | B15: 27 41 16 | C15: BP-10 | D15: AV systems equipment rack | E15: OfficeTech Integrators | F15: 46273 | G15: 46287 | I15: Submitted | J15: 0 | K15: 46391 | L15: 104

Sheet Change_Log
A1: Change # | B1: Date | C1: Title | D1: Origin | E1: Reason | F1: ROM / Proposed | G1: Approved Amount | H1: Status | I1: Budget Code | J1: Schedule Impact (days) | K1: Owner Decision Due | L1: Notes
A2: CO-001 | B2: 46133 | C2: Permit comment revisions | D2: AHJ | E2: Code / permit | F2: 38000 | G2: 38000 | H2: Approved | I2: 00-900 | J2: 0 | K2: 46136 | L2: Added fire-rated shaft detail
A3: CO-002 | B3: 46163 | C3: Footing relocation at telecom ductbank | D3: RFI-002 | E3: Unforeseen condition | F3: 12500 | G3: 12500 | H3: Approved | I3: 03-300 | J3: 0 | K3: 46168
A4: CO-003 | B4: 46183 | C4: Owner conference room AV rough-in | D4: Owner | E4: Scope addition | F4: 42000 | G4: 42000 | H4: Approved | I4: 26-2600 | J4: 0 | K4: 46188
A5: CO-004 | B5: 46181 | C5: Sanitary reroute at fiber bank | D5: RFI-006 | E5: Existing condition | F5: 68500 | G5: 68500 | H5: Approved | I5: 02-200 | J5: 3 | K5: 46183
A6: CO-005 | B6: 46205 | C6: Structural steel connection redesign | D6: Structural | E6: Design coordination | F6: 106000 | G6: 106000 | H6: Approved | I6: 05-500 | J6: 2 | K6: 46210
A7: CO-006 | B7: 46239 | C7: Canopy storefront steel support | D7: RFI-007 | E7: Design coordination | F7: 18000 | G7: 18000 | H7: Approved | I7: 08-800 | J7: 2 | K7: 46244
A8: CO-007 | B8: 46246 | C8: Floor sink additions | D8: Owner/Operations | E8: Scope addition | F8: 42000 | G8: 42000 | H8: Approved | I8: 22-2200 | J8: 0 | K8: 46251
A9: CO-008 | B9: 46265 | C9: Generator feeder wall sleeve | D9: RFI-009 | E9: Design coordination | F9: 22500 | G9: 22500 | H9: Approved | I9: 26-2600 | J9: 2 | K9: 46268
A10: CO-009 | B10: 46266 | C10: Storefront performance upgrade | D10: Owner | E10: Scope enhancement | F10: 95000 | G10: 95000 | H10: Approved | I10: 08-800 | J10: 0 | K10: 46269
A11: CO-010 | B11: 46268 | C11: HVAC controls integration allowance | D11: MEP | E11: Integration risk | F11: 120000 | G11: 120000 | H11: Approved | I11: 23-2300 | J11: 0 | K11: 46273
A12: PCO-011 | B12: 46273 | C12: Expedite electrical gear freight | D12: Electrical | E12: Schedule recovery | F12: 65000 | G12: 0 | H12: Pricing | I12: 26-2600 | J12: -4 | K12: 46280 | L12: Use only if factory ship slips beyond 9/30
A13: PCO-012 | B13: 46273 | C13: Open office lighting control revision | D13: Owner | E13: Scope change | F13: 18000 | G13: 0 | H13: Potential | I13: 26-2600 | J13: 0 | K13: 46283 | L13: Pending owner standards decision

Sheet Risk_Register
A1: Risk ID | B1: Category | C1: Risk Statement | D1: Probability (1-5) | E1: Impact (1-5) | F1: Score | G1: Level | H1: Trigger | I1: Mitigation / Response | J1: Owner | K1: Target Date | L1: Status | M1: Residual Score
A2: R-01 | B2: Schedule | C2: Electrical gear delivery slips beyond required date | D2: 3 | E2: 5 | F2: =D2*E2 -> 15 | G2: =IF(F2>=20,"Critical",IF(F2>=12,"High",IF(F2>=6,"Medium","Low"))) -> High | H2: Factory ship slips past 9/30 | I2: Weekly factory calls; preapprove air/expedite decision; temporary power contingency | J2: PM | K2: 46295 | L2: Open | M2: 8
A3: R-02 | B3: Schedule | C3: Building not weather-tight before interior framing | D3: 3 | E3: 5 | F3: =D3*E3 -> 15 | G3: =IF(F3>=20,"Critical",IF(F3>=12,"High",IF(F3>=6,"Medium","Low"))) -> High | H3: Roof / curtain wall forecast exceeds 9/29 | I3: Daily envelope huddles; split storefront shipments; temporary dry-in membrane | J3: Superintendent | K3: 46294 | L3: Open | M3: 9
A4: R-03 | B4: Cost | C4: Remaining contingency is consumed by owner changes | D4: 4 | E4: 4 | F4: =D4*E4 -> 16 | G4: =IF(F4>=20,"Critical",IF(F4>=12,"High",IF(F4>=6,"Medium","Low"))) -> High | H4: Uncommitted contingency below $200K | I4: Monthly change review; require owner funding for elective scope; freeze finishes by 10/1 | J4: PM | K4: 46296 | L4: Open | M4: 8
A5: R-04 | B5: Quality | C5: Water intrusion at curtain wall transitions | D5: 2 | E5: 5 | F5: =D5*E5 -> 10 | G5: =IF(F5>=20,"Critical",IF(F5>=12,"High",IF(F5>=6,"Medium","Low"))) -> Medium | H5: Failed mockup / first water test | I5: Full-size mockup; envelope consultant review; 100% transition inspection | J5: QA/QC Lead | K5: 46297 | L5: Open | M5: 4
A6: R-05 | B6: Safety | C6: Falls during steel/deck/envelope overlap | D6: 2 | E6: 5 | F6: =D6*E6 -> 10 | G6: =IF(F6>=20,"Critical",IF(F6>=12,"High",IF(F6>=6,"Medium","Low"))) -> Medium | H6: Multiple trades working leading edges | I6: 100% tie-off; controlled access zones; daily leading-edge audit | J6: Safety Manager | K6: 46290 | L6: Open | M6: 4
A7: R-06 | B7: Coordination | C7: MEP clashes cause rework above ceilings | D7: 3 | E7: 4 | F7: =D7*E7 -> 12 | G7: =IF(F7>=20,"Critical",IF(F7>=12,"High",IF(F7>=6,"Medium","Low"))) -> High | H7: Unresolved clash tickets >10 | I7: Weekly BIM clash meeting; sign-off by zone before rough-in | J7: MEP Coordinator | K7: 46283 | L7: Open | M7: 6
A8: R-07 | B8: Stakeholder | C8: Owner late decisions delay finish procurement | D8: 3 | E8: 4 | F8: =D8*E8 -> 12 | G8: =IF(F8>=20,"Critical",IF(F8>=12,"High",IF(F8>=6,"Medium","Low"))) -> High | H8: Decision log overdue >5 business days | I8: Decision due-date dashboard; escalation at OAC; default option identified | J8: PM | K8: 46290 | L8: Open | M8: 6
A9: R-08 | B9: Closeout | C9: Incomplete O&M / training documents delay turnover | D9: 2 | E9: 4 | F9: =D9*E9 -> 8 | G9: =IF(F9>=20,"Critical",IF(F9>=12,"High",IF(F9>=6,"Medium","Low"))) -> Medium | H9: Subcontractor closeout >30 days late | I9: Closeout requirements enforced with pay apps; monthly completeness audit | J9: Project Engineer | K9: 46402 | L9: Open | M9: 3

Sheet Issues_Log
A1: Issue ID | B1: Date Opened | C1: Issue | D1: Impact | E1: Owner | F1: Priority | G1: Due Date | H1: Status | I1: Decision / Next Step | J1: Closed Date
A2: I-001 | B2: 46258 | C2: Steel erection completion slipped one week | D2: Downstream envelope / MEP access | E2: Superintendent | F2: High | G2: 46267 | H2: Complete | I2: Added Saturday crew and resequenced deck pours | J2: 46267
A3: I-002 | B3: 46266 | C3: South elevation framing productivity below plan | D3: Weather-tight milestone at risk | E3: Superintendent | F3: High | G3: 46281 | H3: In Progress | I3: Add second lift and dedicated material runner
A4: I-003 | B4: 46269 | C4: Open office lighting control standard unresolved | D4: Potential owner change and rework | E4: Owner PM | F4: Medium | G4: 46283 | H4: Open | I4: Owner to choose standard package
A5: I-004 | B5: 46274 | C5: MEP clash at grid C7 training room | D5: Rough-in delay in Area A | E5: MEP Coordinator | F5: High | G5: 46279 | H5: In Progress | I5: Issue coordinated spool sketch
A6: I-005 | B6: 46275 | C6: Storefront delivery split; second lot date unconfirmed | D6: South elevation dry-in | E6: PM | F6: High | G6: 46280 | H6: Open | I6: Vendor to confirm second-lot ship notice

Sheet Safety_Log
A1: Date | B1: Event Type | C1: Location | D1: Description | E1: Severity | F1: Responsible Party | G1: Immediate Action | H1: Corrective Action | I1: Status | J1: Recordable?
A2: 46132 | B2: Observation | C2: Site perimeter | D2: Missing cap on exposed rebar | E2: Medium | F2: Sitework Sub | G2: Area barricaded | H2: Install approved rebar caps and inspect all perimeter steel | I2: Closed | J2: No
A3: 46156 | B3: Near Miss | C3: Excavation | D3: Spoil pile too close to trench edge | E3: High | F3: Sitework Sub | G3: Work stopped | H3: Relocate spoils >2 ft; retrain competent person | I3: Closed | J3: No
A4: 46191 | B4: Observation | C4: Slab pour | D4: Extension cord crossing wet work path | E4: Low | F4: Concrete Sub | G4: Cord rerouted | H4: Use overhead cord management | I4: Closed | J4: No
A5: 46232 | B5: Near Miss | C5: Steel erection | D5: Loose bolt dropped from upper level | E5: High | F5: Steel Sub | G5: Drop zone enlarged | H5: Tool tethering and toe-board audit | I5: Closed | J5: No
A6: 46246 | B6: Observation | C6: Roof deck | D6: Worker not maintaining 100% tie-off | E6: Critical | F6: Steel Sub | G6: Worker removed from exposure | H6: Stand-down; documented retraining; foreman spot checks | I6: Closed | J6: No
A7: 46261 | B7: Observation | C7: Loading zone | D7: Forklift pedestrian separation inadequate | E7: Medium | F7: GC | G7: Cones added | H7: Painted pedestrian route and spotter requirement | I7: Closed | J7: No
A8: 46273 | B8: First Aid | C8: North stair | D8: Minor hand cut while handling sheet metal | E8: Low | F8: Mechanical Sub | G8: First aid administered | H8: Glove compliance toolbox talk | I8: Closed | J8: No
A9: 46275 | B9: Observation | C9: South elevation | D9: Scaffold toe board missing | E9: High | F9: Framing Sub | G9: Platform tagged out | H9: Replace toe board before use; scaffold audit | I9: In Progress | J9: No

Sheet Quality_Log
A1: QC ID | B1: Date | C1: Area / Trade | D1: Inspection / Test | E1: Requirement | F1: Result | G1: Deficiency | H1: Responsible Party | I1: Due Date | J1: Status | K1: Verification
A2: QC-001 | B2: 46170 | C2: Foundations | D2: Rebar pre-pour | E2: Per structural drawings | F2: Pass | H2: Concrete Sub | I2: 46170 | J2: Accepted | K2: Special inspector sign-off
A3: QC-002 | B3: 46197 | C3: Foundations | D3: Concrete cylinder test - 7 day | E3: Design 4,000 psi | F3: Pass | H3: Concrete Sub | I3: 46218 | J3: Accepted | K3: Average 3,220 psi at 7 days
A4: QC-003 | B4: 46218 | C4: Slab | D4: FF/FL testing | E4: FF35 / FL25 | F4: Pass | H4: Concrete Sub | I4: 46220 | J4: Accepted | K4: FF41 / FL29
A5: QC-004 | B5: 46238 | C5: Steel | D5: Bolt tension inspection | E5: AISC/RCSC | F5: Pass | H5: Steel Sub | I5: 46238 | J5: Accepted | K5: Inspector report filed
A6: QC-005 | B6: 46259 | C6: Envelope | D6: Air barrier substrate inspection | E6: Manufacturer requirements | F6: Fail | G6: Fastener spacing / open joints | H6: Framing Sub | I6: 46262 | J6: Corrected | K6: Reinspection passed 8/28
A7: QC-006 | B7: 46267 | C7: Roof | D7: TPO seam probe test | E7: 100% seams | F7: Pass | H7: Roofing Sub | I7: 46267 | J7: Accepted
A8: QC-007 | B8: 46274 | C8: MEP Area A | D8: Above-ceiling rough-in walk | E8: Approved coordination model | F8: Fail | G8: Duct/sprinkler conflict grid C7 | H8: MEP Subs | I8: 46279 | J8: Open | K8: Reinspect after RFI resolution
A9: QC-008 | B9: 46275 | C9: South Elevation | D9: Exterior framing plumb/tolerance | E9: 1/8 in over 10 ft | F9: Pass | H9: Framing Sub | I9: 46275 | J9: Accepted

Sheet Stakeholders
A1: Stakeholder | B1: Organization / Role | C1: Influence | D1: Interest | E1: Communication Need | F1: Cadence | G1: Channel | H1: Owner | I1: Success Measure
A2: Executive Sponsor | B2: Owner / COO | C2: High | D2: High | E2: Budget, schedule, major risk, decisions | F2: Monthly | G2: Executive report | H2: PM | I2: No surprises; decisions within 3 days
A3: Owner Project Manager | B3: Owner | C3: High | D3: High | E3: Daily decisions, change control, coordination | F3: Weekly + as needed | G3: OAC / email | H3: PM | I3: Decision log current
A4: Facilities Director | B4: Owner Operations | C4: Medium | D4: High | E4: Maintainability, equipment access, training | F4: Biweekly | G4: Field walk / meeting | H4: PM | I4: Operations sign-off
A5: Architect | B5: Design Team | C5: High | D5: High | E5: RFIs, submittals, design intent | F5: Weekly | G5: OAC / Procore-style logs | H5: PM | I5: Average RFI turnaround <5 days
A6: MEP Engineers | B6: Design Team | C6: High | D6: Medium | E6: Coordination, field clarifications | F6: Weekly | G6: BIM / RFI | H6: MEP Coordinator | I6: Clashes closed before install
A7: General Contractor Team | B7: Delivery Team | C7: High | D7: High | E7: Schedule, safety, quality, costs | F7: Daily | G7: Huddle / dashboard | H7: PM | I7: Milestones achieved
A8: Subcontractors | B8: Trade Partners | C8: Medium | D8: High | E8: Look-ahead, constraints, safety, quality | F8: Weekly | G8: Trade meeting | H8: Superintendent | I8: PPC >80%
A9: AHJ / Inspectors | B9: Regulatory | C9: High | D9: Medium | E9: Inspection readiness, code compliance | F9: As required | G9: Inspection request | H9: Project Engineer | I9: Pass first inspection
A10: Finance | B10: Owner Finance | C10: Medium | D10: Medium | E10: Forecast, cash flow, change exposure | F10: Monthly | G10: Cost report | H10: PM | I10: Forecast accuracy +/-2%
A11: IT / Security | B11: Owner IT | C11: Medium | D11: High | E11: AV/data/access control decisions | F11: Biweekly | G11: Coordination meeting | H11: PM | I11: Systems ready before move-in

Sheet Meeting_Actions
A1: Action ID | B1: Meeting | C1: Date Opened | D1: Action | E1: Owner | F1: Due Date | G1: Priority | H1: Status | I1: Dependency | J1: Completion Note
A2: A-001 | B2: OAC | C2: 46268 | D2: Confirm storefront second-shipment date | E2: PM | F2: 46280 | G2: High | H2: In Progress | I2: BP-05 | J2: Vendor escalation underway
A3: A-002 | B3: Trade Coordination | C3: 46273 | D3: Resolve grid C7 duct/sprinkler clash | E3: MEP Coordinator | F3: 46279 | G3: High | H3: In Progress | I3: RFI-013 | J3: Coordinated sketch due 9/14
A4: A-003 | B4: OAC | C4: 46275 | D4: Owner select lighting control standard | E4: Owner PM | F4: 46283 | G4: High | H4: Open | I4: PCO-012 | J4: Three options issued
A5: A-004 | B5: Safety | C5: 46275 | D5: Close scaffold toe-board observation | E5: Framing Foreman | F5: 46276 | G5: High | H5: In Progress | I5: Safety 9/10 | J5: Reinspection scheduled
A6: A-005 | B6: Procurement | C6: 46274 | D6: Confirm electrical gear factory ship notice | E6: Electrical PM | F6: 46283 | G6: High | H6: Open | I6: R-01 | J6: Weekly vendor update
A7: A-006 | B7: Quality | C7: 46274 | D7: Reinspect MEP rough-in at training room | E7: QA/QC Lead | F7: 46280 | G7: Medium | H7: Open | I7: QC-007 | J7: After clash correction
A8: A-007 | B8: OAC | C8: 46268 | D8: Freeze Level 1 finish selections | E8: Facilities Director | F8: 46282 | G8: Medium | H8: In Progress | I8: R-07 | J8: Final samples in owner review
A9: A-008 | B9: Schedule | C9: 46276 | D9: Add second lift at south elevation | E9: Superintendent | F9: 46279 | G9: High | H9: Open | I9: I-002 | J9: Recovery plan approved

Sheet Closeout
A1: Item ID | B1: Category | C1: Requirement | D1: Responsible Party | E1: Planned Due | F1: Actual / Forecast | G1: Status | H1: % Complete | I1: Retention Link | J1: Notes
A2: C-001 | B2: Permits | C2: Final building inspection / CO | D2: PM/Architect | E2: 46458 | F2: 46458 | G2: Not Started | H2: 0 | I2: Final payment | J2: AHJ inspection matrix maintained
A3: C-002 | B3: Commissioning | C3: Functional performance testing | D3: CxA / MEP | E3: 46444 | F3: 46444 | G3: Not Started | H3: 0 | I3: MEP retention
A4: C-003 | B4: O&M Manuals | C4: Approved electronic O&M manuals | D4: All Trades | E4: 46430 | F4: 46437 | G4: Not Started | H4: 0 | I4: 10% trade retention | J4: Monthly completeness audit starts Nov
A5: C-004 | B5: Training | C5: Owner equipment training | D5: MEP / Vendors | E5: 46451 | F5: 46451 | G5: Not Started | H5: 0 | I5: MEP retention | J5: Record sessions
A6: C-005 | B6: As-Builts | C6: Redline and final record drawings | D6: All Trades | E6: 46437 | F6: 46444 | G6: Not Started | H6: 0 | I6: 5% trade retention | J6: Weekly redline spot checks
A7: C-006 | B7: Warranties | C7: Warranty certificates and start dates | D7: All Trades | E7: 46451 | F7: 46451 | G7: Not Started | H7: 0 | I7: Final payment
A8: C-007 | B8: Punch List | C8: Architect/owner punch complete | D8: GC / Subs | E8: 46451 | F8: 46451 | G8: Not Started | H8: 0 | I8: Final payment | J8: Digital punch by room
A9: C-008 | B9: Training | C9: IT / security systems turnover | D9: OfficeTech | E9: 46451 | F9: 46451 | G9: Not Started | H9: 0 | I9: Vendor final
A10: C-009 | B10: Financial | C10: Final change reconciliation | D10: PM / Finance | E10: 46458 | F10: 46458 | G10: Not Started | H10: 0 | I10: GC final | J10: No open PCOs at substantial completion
A11: C-010 | B11: Lessons Learned | C11: Project retrospective and KPI closeout | D11: PM | E11: 46465 | F11: 46465 | G11: Not Started | H11: 0 | I11: N/A

Sheet Categories
A1: Schedule Status | B1: Cost Status | C1: RFI Status | D1: Submittal Status | E1: Change Status | F1: Risk Level | G1: Action Status | H1: Safety Severity | I1: QC Status | J1: Closeout Status | K1: Priority
A2: Not Started | B2: On Budget | C2: Open | D2: Not Submitted | E2: Potential | F2: Low | G2: Open | H2: Low | I2: Open | J2: Not Started | K2: Low
A3: In Progress | B3: Watch | C3: Answered | D3: Submitted | E3: Pricing | F3: Medium | G3: In Progress | H3: Medium | I3: Corrected | J3: In Progress | K3: Medium
A4: Complete | B4: Over Budget | C4: Closed | D4: Approved | E4: Approved | F4: High | G4: Complete | H4: High | I4: Accepted | J4: Complete | K4: High
A5: Delayed | C5: Void | D5: Revise & Resubmit | E5: Rejected | F5: Critical | H5: Critical | I5: Rejected | J5: Blocked | K5: Critical

Sheet CPM_Gantt
A1: WBS | B1: Activity | C1: Pred. | D1: Baseline Start | E1: Baseline Finish | F1: Forecast Start | G1: Forecast Finish | H1: Dur. | I1: Critical | J1: Float (d) | K1: Variance (d) | L1: Status | M1: GANTT TIMELINE (weekly)
A2: 1.1 | B2: Owner program validation | D2: 46034 | E2: 46045 | F2: 46034 | G2: 46044 | H2: 12 | I2: No | J2: 7 | K2: -1 | L2: Complete | M2: 46035 | N2: 46042 | O2: 46049 | P2: 46056 | Q2: 46063 | R2: 46070 | S2: 46077 | T2: 46084 | U2: 46091 | V2: 46098 | W2: 46105 | X2: 46112 | Y2: 46119 | Z2: 46126 | AA2: 46133 | AB2: 46140 | AC2: 46147 | AD2: 46154 | AE2: 46161 | AF2: 46168 | AG2: 46175 | AH2: 46182 | AI2: 46189 | AJ2: 46196 | AK2: 46203 | AL2: 46210 | AM2: 46217 | AN2: 46224 | AO2: 46231 | AP2: 46238 | AQ2: 46245 | AR2: 46252 | AS2: 46259 | AT2: 46266 | AU2: 46273 | AV2: 46280 | AW2: 46287 | AX2: 46294 | AY2: 46301 | AZ2: 46308 | BA2: 46315 | BB2: 46322 | BC2: 46329 | BD2: 46336 | BE2: 46343 | BF2: 46350 | BG2: 46357 | BH2: 46364 | BI2: 46371 | BJ2: 46378 | BK2: 46385 | BL2: 46392 | BM2: 46399 | BN2: 46406 | BO2: 46413 | BP2: 46420 | BQ2: 46427 | BR2: 46434 | BS2: 46441 | BT2: 46448 | BU2: 46455 | BV2: 46462 | BW2: 46469 | BX2: 46476
A3: 1.2 | B3: Design development / 60% CDs | C3: 1.1 | D3: 46041 | E3: 46073 | F3: 46041 | G3: 46077 | H3: 33 | I3: Yes | J3: 0 | K3: 4 | L3: Complete | M3: ■ | N3: ■
A4: 1.3 | B4: 100% construction documents | C4: 1.2 | D4: 46076 | E4: 46108 | F4: 46078 | G4: 46114 | H4: 33 | I4: Yes | J4: 0 | K4: 6 | L4: Complete | N4: ■ | O4: ■ | P4: ■ | Q4: ■ | R4: ■ | S4: ■
A5: 1.4 | B5: Permit review and issuance | C5: 1.3 | D5: 46083 | E5: 46122 | F5: 46083 | G5: 46126 | H5: 40 | I5: Yes | J5: 0 | K5: 4 | L5: Complete | T5: ■ | U5: ■ | V5: ■ | W5: ■ | X5: ■
A6: 1.5 | B6: Bid packages and subcontract awards | C6: 1.2 | D6: 46069 | E6: 46115 | F6: 46069 | G6: 46119 | H6: 47 | I6: No | J6: 7 | K6: 4 | L6: Complete | T6: ■ | U6: ■ | V6: ■ | W6: ■ | X6: ■ | Y6: ■ | Z6: ■
A7: 2.1 | B7: Site mobilization / temporary controls | C7: 1.4,1.5 | D7: 46125 | E7: 46136 | F7: 46127 | G7: 46136 | H7: 12 | I7: Yes | J7: 0 | K7: 0 | L7: Complete | R7: ■ | S7: ■ | T7: ■ | U7: ■ | V7: ■ | W7: ■ | X7: ■ | Y7: ■
A8: 2.2 | B8: Clearing and erosion controls | C8: 2.1 | D8: 46132 | E8: 46150 | F8: 46134 | G8: 46153 | H8: 19 | I8: Yes | J8: 0 | K8: 3 | L8: Complete | AA8: ■
A9: 2.3 | B9: Mass grading and underground utilities | C9: 2.2 | D9: 46146 | E9: 46185 | F9: 46148 | G9: 46191 | H9: 40 | I9: Yes | J9: 0 | K9: 6 | L9: Complete | AB9: ■ | AC9: ■
A10: 3.1 | B10: Footings and grade beams | C10: 2.3 | D10: 46167 | E10: 46192 | F10: 46170 | G10: 46197 | H10: 26 | I10: Yes | J10: 0 | K10: 5 | L10: Complete | AD10: ■ | AE10: ■ | AF10: ■ | AG10: ■ | AH10: ■ | AI10: ■
A11: 3.2 | B11: Slab-on-grade | C11: 3.1 | D11: 46188 | E11: 46213 | F11: 46193 | G11: 46218 | H11: 26 | I11: Yes | J11: 0 | K11: 5 | L11: Complete | AG11: ■ | AH11: ■ | AI11: ■ | AJ11: ■
A12: 4.1 | B12: Structural steel fabrication | C12: 1.5 | D12: 46132 | E12: 46206 | F12: 46134 | G12: 46213 | H12: 75 | I12: Yes | J12: 0 | K12: 7 | L12: Complete | AJ12: ■ | AK12: ■ | AL12: ■ | AM12: ■
A13: 4.2 | B13: Structural steel erection | C13: 3.2,4.1 | D13: 46216 | E13: 46255 | F13: 46219 | G13: 46262 | H13: 40 | I13: Yes | J13: 0 | K13: 7 | L13: Complete | AB13: ■ | AC13: ■ | AD13: ■ | AE13: ■ | AF13: ■ | AG13: ■ | AH13: ■ | AI13: ■ | AJ13: ■ | AK13: ■ | AL13: ■
A14: 4.3 | B14: Metal deck and concrete elevated slab | C14: 4.2 | D14: 46237 | E14: 46269 | F14: 46244 | G14: 46276 | H14: 33 | I14: Yes | J14: 0 | K14: 7 | L14: In Progress | AN14: ■ | AO14: ■ | AP14: ■ | AQ14: ■ | AR14: ■ | AS14: ■
A15: 5.1 | B15: Exterior framing and sheathing | C15: 4.2 | D15: 46251 | E15: 46290 | F15: 46258 | G15: 46297 | H15: 40 | I15: Yes | J15: 0 | K15: 7 | L15: In Progress | AQ15: ■ | AR15: ■ | AS15: ■ | AT15: ■ | AU15: ■
A16: 5.2 | B16: Roofing system | C16: 4.3 | D16: 46265 | E16: 46290 | F16: 46268 | G16: 46297 | H16: 26 | I16: Yes | J16: 0 | K16: 7 | L16: In Progress | AS16: ■ | AT16: ■ | AU16: ■ | AV16: ■ | AW16: ■ | AX16: ■
A17: 5.3 | B17: Curtain wall / storefront | C17: 5.1 | D17: 46272 | E17: 46311 | F17: 46274 | G17: 46313 | H17: 40 | I17: No | J17: 7 | K17: 2 | L17: In Progress | AU17: ■ | AV17: ■ | AW17: ■ | AX17: ■
A18: 6.1 | B18: Underground electrical and plumbing | C18: 2.3 | D18: 46160 | E18: 46220 | F18: 46162 | G18: 46224 | H18: 61 | I18: No | J18: 7 | K18: 4 | L18: Complete | AV18: ■ | AW18: ■ | AX18: ■ | AY18: ■ | AZ18: ■
A19: 6.2 | B19: MEP overhead rough-in - Area A | C19: 4.3 | D19: 46258 | E19: 46297 | F19: 46265 | G19: 46304 | H19: 40 | I19: Yes | J19: 0 | K19: 7 | L19: In Progress | AF19: ■ | AG19: ■ | AH19: ■ | AI19: ■ | AJ19: ■ | AK19: ■ | AL19: ■ | AM19: ■ | AN19: ■
A20: 6.3 | B20: MEP overhead rough-in - Area B | C20: 6.2 | D20: 46279 | E20: 46318 | F20: 46286 | G20: 46325 | H20: 40 | I20: Yes | J20: 0 | K20: 7 | L20: Not Started | AT20: ■ | AU20: ■ | AV20: ■ | AW20: ■ | AX20: ■ | AY20: ■
A21: 6.4 | B21: Main electrical gear delivery | C21: 1.5 | D21: 46146 | E21: 46304 | F21: 46146 | G21: 46306 | H21: 159 | I21: Yes | J21: 0 | K21: 2 | L21: In Progress | AW21: ■ | AX21: ■ | AY21: ■ | AZ21: ■ | BA21: ■ | BB21: ■
A22: 6.5 | B22: AHU / RTU delivery and set | C22: 1.5 | D22: 46153 | E22: 46283 | F22: 46153 | G22: 46285 | H22: 131 | I22: Yes | J22: 0 | K22: 2 | L22: In Progress | AC22: ■ | AD22: ■ | AE22: ■ | AF22: ■ | AG22: ■ | AH22: ■ | AI22: ■ | AJ22: ■ | AK22: ■ | AL22: ■ | AM22: ■ | AN22: ■ | AO22: ■ | AP22: ■ | AQ22: ■ | AR22: ■ | AS22: ■ | AT22: ■ | AU22: ■ | AV22: ■ | AW22: ■ | AX22: ■ | AY22: ■
A23: 7.1 | B23: Interior metal framing | C23: 5.2,6.2 | D23: 46293 | E23: 46332 | F23: 46300 | G23: 46339 | H23: 40 | I23: Yes | J23: 0 | K23: 7 | L23: Not Started | AD23: ■ | AE23: ■ | AF23: ■ | AG23: ■ | AH23: ■ | AI23: ■ | AJ23: ■ | AK23: ■ | AL23: ■ | AM23: ■ | AN23: ■ | AO23: ■ | AP23: ■ | AQ23: ■ | AR23: ■ | AS23: ■ | AT23: ■ | AU23: ■ | AV23: ■
A24: 7.2 | B24: Drywall / tape / finish | C24: 7.1 | D24: 46314 | E24: 46360 | F24: 46321 | G24: 46367 | H24: 47 | I24: Yes | J24: 0 | K24: 7 | L24: Not Started | AY24: ■ | AZ24: ■ | BA24: ■ | BB24: ■ | BC24: ■ | BD24: ■
A25: 7.3 | B25: Ceilings and flooring | C25: 7.2 | D25: 46349 | E25: 46402 | F25: 46349 | G25: 46402 | H25: 54 | I25: No | J25: 7 | K25: 0 | L25: Not Started | BB25: ■ | BC25: ■ | BD25: ■ | BE25: ■ | BF25: ■ | BG25: ■ | BH25: ■
A26: 7.4 | B26: Millwork / doors / hardware | C26: 7.2 | D26: 46356 | E26: 46409 | F26: 46356 | G26: 46409 | H26: 54 | I26: No | J26: 7 | K26: 0 | L26: Not Started | BF26: ■ | BG26: ■ | BH26: ■ | BI26: ■ | BJ26: ■ | BK26: ■ | BL26: ■ | BM26: ■
A27: 7.5 | B27: Painting and final finishes | C27: 7.2 | D27: 46363 | E27: 46416 | F27: 46363 | G27: 46416 | H27: 54 | I27: No | J27: 7 | K27: 0 | L27: Not Started | BG27: ■ | BH27: ■ | BI27: ■ | BJ27: ■ | BK27: ■ | BL27: ■ | BM27: ■ | BN27: ■
A28: 8.1 | B28: Paving, curb, sidewalks | C28: 5.1 | D28: 46300 | E28: 46339 | F28: 46300 | G28: 46339 | H28: 40 | I28: No | J28: 7 | K28: 0 | L28: Not Started | BH28: ■ | BI28: ■ | BJ28: ■ | BK28: ■ | BL28: ■ | BM28: ■ | BN28: ■ | BO28: ■
A29: 8.2 | B29: Landscaping and site furnishings | C29: 8.1 | D29: 46391 | E29: 46423 | F29: 46391 | G29: 46423 | H29: 33 | I29: No | J29: 7 | K29: 0 | L29: Not Started | AY29: ■ | AZ29: ■ | BA29: ■ | BB29: ■ | BC29: ■ | BD29: ■
A30: 9.1 | B30: MEP startup and controls checkout | C30: 6.4,6.5,7.3 | D30: 46398 | E30: 46430 | F30: 46405 | G30: 46437 | H30: 33 | I30: Yes | J30: 0 | K30: 7 | L30: Not Started | BL30: ■ | BM30: ■ | BN30: ■ | BO30: ■ | BP30: ■
A31: 9.2 | B31: TAB / functional performance testing | C31: 9.1 | D31: 46419 | E31: 46444 | F31: 46426 | G31: 46451 | H31: 26 | I31: Yes | J31: 0 | K31: 7 | L31: Not Started | BN31: ■ | BO31: ■ | BP31: ■ | BQ31: ■ | BR31: ■
A32: 9.3 | B32: Punch list and deficiency correction | C32: 7.5,9.2 | D32: 46433 | E32: 46451 | F32: 46440 | G32: 46458 | H32: 19 | I32: Yes | J32: 0 | K32: 7 | L32: Not Started | BQ32: ■ | BR32: ■ | BS32: ■ | BT32: ■
A33: 9.4 | B33: Owner training / O&M turnover | C33: 9.1 | D33: 46440 | E33: 46458 | F33: 46440 | G33: 46458 | H33: 19 | I33: No | J33: 7 | K33: 0 | L33: Not Started | BS33: ■ | BT33: ■ | BU33: ■
A34: 9.5 | B34: Certificate of Occupancy | C34: 9.3 | D34: 46454 | E34: 46458 | F34: 46461 | G34: 46465 | H34: 5 | I34: Yes | J34: 0 | K34: 7 | L34: Not Started | BS34: ■ | BT34: ■ | BU34: ■
A35: 9.6 | B35: Final completion / handover | C35: 9.4,9.5 | D35: 46461 | E35: 46465 | F35: 46468 | G35: 46472 | H35: 5 | I35: Yes | J35: 0 | K35: 7 | L35: Not Started | BV35: ■
BW36: ■

Sheet Earned_Value
A1: Month | B1: PV | C1: EV | D1: AC | E1: SPI | F1: CPI | G1: SV | H1: CV | J1: EARNED VALUE PERFORMANCE | STATUS DATE 09/15/2026
A2: 46023 | B2: 450000 | C2: 430000 | D2: 470000 | E2: 0.95555556 | F2: 0.91489362 | G2: -20000 | H2: -40000
A3: 46054 | B3: 1200000 | C3: 1150000 | D3: 1240000 | E3: 0.95833333 | F3: 0.92741935 | G3: -50000 | H3: -90000 | J3: Metric | K3: Value | M3: Metric | N3: Value
A4: 46082 | B4: 2350000 | C4: 2250000 | D4: 2380000 | E4: 0.95744681 | F4: 0.94537815 | G4: -100000 | H4: -130000 | J4: BAC | K4: 20600000 | M4: CPI | N4: 1.2325012
A5: 46113 | B5: 4100000 | C5: 3920000 | D5: 4080000 | E5: 0.95609756 | F5: 0.96078431 | G5: -180000 | H5: -160000 | J5: PV | K5: 13050000 | M5: EAC (CPI) | N5: 16713979
A6: 46143 | B6: 6250000 | C6: 5980000 | D6: 6100000 | E6: 0.9568 | F6: 0.98032787 | G6: -270000 | H6: -120000 | J6: EV | K6: 12590000 | M6: VAC | N6: 3886020.7
A7: 46174 | B7: 8350000 | C7: 7960000 | D7: 8050000 | E7: 0.95329341 | F7: 0.98881988 | G7: -390000 | H7: -90000 | J7: AC | K7: 10215000 | M7: TCPI (BAC) | N7: 0.77130477
A8: 46204 | B8: 10100000 | C8: 9720000 | D8: 9550000 | E8: 0.96237624 | F8: 1.017801 | G8: -380000 | H8: 170000 | J8: SPI | K8: 0.96475096 | M8: Schedule Var. | N8: -460000
A9: 46235 | B9: 11850000 | C9: 11380000 | D9: 10050000 | E9: 0.96033755 | F9: 1.1323383 | G9: -470000 | H9: 1330000
A10: 46266 | B10: 13050000 | C10: 12590000 | D10: 10215000 | E10: 0.96475096 | F10: 1.2325012 | G10: -460000 | H10: 2375000

Sheet Completed_Forms
A1: COMPLETED CONSTRUCTION CONTROL FORMS | PORTFOLIO SAMPLES
A3: Form ID | B3: Type | C3: Subject | D3: Responsible | E3: Status | F3: Disposition / Key Record | G3: Cycle Time | H3: Cost Impact
A4: RFI-006 | B4: RFI | C4: Underground utility conflict at east service yard | D4: Civil/MEP | E4: Closed | F4: Relocate storm line 4'-0" south; no structural impact | G4: 4 days | H4: $18,500
A5: SUB-042 | B5: Submittal | C5: Main switchgear product data and shop drawings | D5: Electrical | E5: Approved as Noted | F5: Release fabrication with revised breaker labeling | G5: 6 days | H5: $0
A6: PCO-011 | B6: Potential Change | C6: Owner-requested storefront finish upgrade | D6: Owner/Glazing | E6: Approved | F6: Incorporated into CO-004 after pricing validation | G6: 9 days | H6: $95,000
A7: DR-0915 | B7: Daily Report | C7: Steel/deck/envelope/MEP field operations | D7: Superintendent | E7: Complete | F7: 84 workers; 0 incidents; rain 0.2 in.; south elevation recovery crew added | G7: 1 day | H7: N/A
A8: MTG-028 | B8: OAC Minutes | C8: Weekly owner-architect-contractor meeting | D8: PM | E8: Complete | F8: Decisions: protect 9/29 dry-in; maintain gear expedite gate; reject noncritical owner add | G8: 60 min | H8: N/A
A10: SAMPLE OAC MEETING MINUTES | 09/15/2026
A11: Item | B11: Topic | C11: Discussion / Decision | D11: Owner | E11: Due | F11: Status | G11: Impact | H11: Reference
A12: 1 | B12: Weather-tight milestone | C12: South elevation recovery crew approved; resequence north glazing prep in parallel. | D12: Superintendent | E12: 09/18/26 | F12: Open | G12: Protects critical path | H12: SCH-5.1/5.2
A13: 2 | B13: Electrical gear | C13: Factory ship date 9/28 confirmed. Expedite only if ship date slips >3 days. | D13: PM/Electrical | E13: 09/22/26 | F13: Open | G13: Avoid unnecessary premium | H13: PROC-004
A14: 3 | B14: MEP clash Grid C7 | C14: RFI response accepted; reroute duct branch before ceiling close-in. | D14: MEP Lead | E14: 09/17/26 | F14: Open | G14: 2-day local recovery | H14: RFI-014
A15: 4 | B15: Owner changes | C15: Defer elective conference-room AV upgrade until contingency review. | D15: Owner/PM | E15: 09/21/26 | F15: Open | G15: Protect contingency | H15: PCO-013
A16: 5 | B16: Safety | C16: Close scaffold access observation before next shift. | D16: Superintendent | E16: 09/16/26 | F16: Closed | G16: Zero recordables maintained | H16: SAFE-008

Sheet Portfolio_Case_Study
A1: CORPORATE OPERATIONS CENTER | CONSTRUCTION PM CASE STUDY
A3: Project | B3: 75,000 SF Ground-Up Corporate Operations Center
A4: Delivery | B4: Corporate commercial construction simulation
A5: Baseline Budget | B5: $20.6M
A6: Status Date | B6: 09/15/2026
A7: Baseline Finish | B7: 03/19/2027
A8: Current Health | B8: AMBER - schedule recovery / contingency watch
A9: Safety | B9: 0 recordable incidents
A10: Role | B10: Construction Project Manager - Portfolio Simulation
A12: BUSINESS / DELIVERY CHALLENGE
A13: Deliver a new corporate operations center while controlling a weather-sensitive envelope sequence, long-lead electrical equipment, active design coordination, owner changes, safety, quality, and commissioning requirements. By September, critical envelope and Area A MEP work had slipped, creating pressure on the weather-tight milestone and downstream interiors.
A17: PM ACTIONS & CONTROLS
A18: Built and maintained an integrated control system covering schedule, budget/forecast, procurement, RFIs, submittals, changes, risks, issues, safety, quality, meetings, stakeholders, and closeout. Used critical-path review and a recovery crew to protect dry-in; established weekly factory calls for electrical gear; enforced formal RFI/submittal and change-control gates; tracked contingency consumption and forecast-at-completion; and escalated executive decisions through a concise monthly status report.
A24: MEASURABLE PROJECT OUTCOMES AT STATUS DATE
A25: Metric | B25: Result | C25: Why it matters | D25: PM evidence
A26: Forecast | B26: $20.55M FAC vs $21.057M revised budget | C26: Forecast remains within authorized funding | D26: Budget_Cost / Dashboard
A27: Schedule | B27: 49.9% actual vs 51.7% planned | C27: 1.8 pp behind; recovery actions active | D27: CPM_Gantt / Master_Schedule
A28: Safety | B28: 0 recordables | C28: Maintains workforce and delivery continuity | D28: Safety_Log
A29: Controls | B29: 3 open RFIs; long-leads released | C29: Decision cycle and procurement exposure actively managed | D29: RFI_Log / Procurement
